Workbook

Sheet دليل الاستخدام
A1: حالات اختبار نظام معرض قويدر
A3: الهدف | B3: التأكد من أن كل أقسام النظام تعمل كما هو متوقع قبل الاعتماد عليه في العمل اليومي.
A4: عدد الحالات | B4: 149 حالة في 20 قسمًا.
A5: طريقة الاستخدام | B5: 1) افتح ورقة «حالات الاختبار». 2) نفّذ خطوات كل حالة بالدور المذكور. 3) اختر النتيجة من القائمة واكتب ما حدث فعلًا إذا اختلف. 4) راجع ورقة «الملخص» لمعرفة نسبة الإنجاز والنجاح.
A6: الخانات التي تعبّئها | B6: الخانات الصفراء فقط: النتيجة، النتيجة الفعلية / الملاحظات، المُختبِر، تاريخ الاختبار. باقي الأعمدة ثابتة.
A7: قيم «النتيجة» | B7: نجح: النتيجة مطابقة للمتوقع. فشل: النتيجة مختلفة (اكتب ما حدث). محجوب: لا يمكن التنفيذ الآن (مثلًا لا يوجد آيفون). لم يُختبر: لم تُنفّذ بعد.
A8: مثال تعبئة | B8: النتيجة: فشل | النتيجة الفعلية: «الفاتورة بقيت آجل بعد تأكيد الحوالة» | المُختبِر: محمد | التاريخ: 2026-10-26
A9: مغطى آليًا | B9: «نعم» تعني أن هذه الحالة يفحصها أيضًا اختبار آلي يعمل مع كل تعديل على الكود (اسمه في عمود «الاختبار الآلي»). الاختبار اليدوي يبقى مطلوبًا للتأكد من الشاشات على أجهزتك.
A10: الأدوار | B10: مدير النظام، مدير المعرض، موظف مبيعات، أمين مخزن، محاسب، مشاهد. أنشئ مستخدمًا تجريبيًا لكل دور قبل البدء.
A11: تحذير | B11: حالات «تصفير النظام» تمسح البيانات نهائيًا: نفّذها فقط على نسخة تجريبية أو قبل إدخال بيانات حقيقية.
A12: ترقيم الحالات | B12: رمز القسم + رقم، مثل POS-03 = الحالة الثالثة في نقطة البيع.
A14: الأقسام
A15: AUTH | B15: تسجيل الدخول والحساب — 10 حالة
A16: USR | B16: المستخدمون والأدوار والصلاحيات — 10 حالة
A17: SET | B17: الإعدادات وسجل العمليات والتصفير — 9 حالة
A18: CAT | B18: الأصناف — 4 حالة
A19: PRD | B19: المنتجات والباركود — 14 حالة
A20: INV | B20: المخزون والجرد — 6 حالة
A21: PUR | B21: الموردون والمشتريات — 7 حالة
A22: POS | B22: نقطة البيع — 16 حالة
A23: SAL | B23: فواتير المبيعات والمرتجعات — 11 حالة
A24: CUS | B24: العملاء والديون — 5 حالة
A25: TRF | B25: الحوالات — 6 حالة
A26: ACC | B26: الحسابات المالية والتحويلات — 5 حالة
... A34: CON | B34: التزامن وسلامة البيانات — 4 حالة

Sheet حالات الاختبار
A1: رقم الحالة | B1: القسم | C1: السيناريو | D1: الدور | E1: المتطلبات المسبقة | F1: خطوات التنفيذ | G1: النتيجة المتوقعة | H1: الأولوية | I1: مغطى آليًا | J1: الاختبار الآلي | K1: النتيجة | L1: النتيجة الفعلية / الملاحظات | M1: المُختبِر | N1: تاريخ الاختبار
A2: AUTH-01 | B2: تسجيل الدخول والحساب | C2: دخول ناجح ببيانات صحيحة | D2: أي مستخدم | E2: مستخدم فعّال | F2: 1. افتح صفحة الدخول 2. اكتب اسم المستخدم وكلمة المرور الصحيحة 3. اضغط «دخول» | G2: تفتح لوحة التحكم ويظهر اسم المستخدم أعلى الصفحة | H2: عالية | I2: نعم | J2: Login_with_valid_credentials_returns_token_and_all_admin_permissions | K2: نجح | L2: مطابق للمتوقع | M2: Claude (اختبار آلي للشاشات) | N2: 46321
A3: AUTH-02 | B3: تسجيل الدخول والحساب | C3: دخول بكلمة مرور خاطئة | D3: أي مستخدم | E3: — | F3: 1. اكتب اسم مستخدم صحيح وكلمة مرور خاطئة 2. اضغط «دخول» | G3: رسالة عربية «اسم المستخدم أو كلمة المرور غير صحيحة» ولا يتم الدخول | H3: عالية | I3: نعم | J3: Login_with_wrong_password_is_rejected_with_arabic_message | K3: نجح | L3: مطابق للمتوقع | M3: Claude (اختبار آلي للشاشات) | N3: 46321
A4: AUTH-03 | B4: تسجيل الدخول والحساب | C4: قفل مؤقت بعد 5 محاولات خاطئة | D4: أي مستخدم | E4: حساب تجريبي (ليس حساب المدير الأساسي) | F4: 1. أدخل كلمة مرور خاطئة 5 مرات متتالية 2. حاول مرة سادسة بكلمة المرور الصحيحة | G4: رسالة «تم إيقاف الدخول مؤقتًا…» ثم يسمح بالدخول بعد بضع دقائق | H4: متوسطة | I4: نعم | J4: Five_wrong_passwords_lock_the_account_even_for_the_right_one | K4: نجح | L4: بعد 5 محاولات خاطئة رُفضت كلمة المرور الصحيحة برسالة الإيقاف المؤقت | M4: Claude (اختبار آلي للشاشات) | N4: 46321
A5: AUTH-04 | B5: تسجيل الدخول والحساب | C5: مستخدم جديد يُجبر على تغيير كلمة المرور | D5: أي مستخدم | E5: مستخدم أنشأه المدير الآن | F5: 1. ادخل بكلمة المرور المؤقتة 2. حاول فتح أي صفحة | G5: يُحوَّل إلى صفحة تغيير كلمة المرور ولا يستطيع استخدام النظام قبل تغييرها | H5: عالية | I5: نعم | J5: New_user_must_change_password_before_using_the_api | K5: نجح | L5: مطابق للمتوقع | M5: Claude (اختبار آلي للشاشات) | N5: 46321
A6: AUTH-05 | B6: تسجيل الدخول والحساب | C6: تغيير كلمة المرور بكلمة حالية خاطئة | D6: أي مستخدم | E6: مسجّل دخول | F6: 1. الحساب الشخصي ← تغيير كلمة المرور 2. اكتب كلمة حالية خاطئة وكلمة جديدة 3. احفظ | G6: خطأ تحت حقل «كلمة المرور الحالية» ولا تتغير | H6: متوسطة | I6: نعم | J6: Change_password_validation_errors_are_keyed_by_camel_case_field | K6: نجح | L6: مطابق للمتوقع | M6: Claude (اختبار آلي للشاشات) | N6: 46321
A7: AUTH-06 | B7: تسجيل الدخول والحساب | C7: تغيير كلمة المرور بنجاح | D7: أي مستخدم | E7: مسجّل دخول | F7: 1. غيّر كلمة المرور بشكل صحيح 2. سجّل خروج 3. ادخل بالكلمة الجديدة | G7: الدخول بالكلمة الجديدة يعمل والقديمة لا تعمل | H7: عالية | I7: نعم | J7: After_changing_the_password_only_the_new_one_works | K7: نجح | L7: خطأ اكتُشف وأُصلح: بعد تغيير كلمة المرور الإجبارية كان الموظف يرجع لصفحة تغيير كلمة المرور كأن التغيير فشل. الآن يدخل للوحة التحكم. | M7: Claude (اختبار آلي للشاشات) | N7: 46321
A8: AUTH-07 | B8: تسجيل الدخول والحساب | C8: الجلسة تبقى بعد إغلاق التطبيق وفتحه | D8: أي مستخدم | E8: مسجّل دخول | F8: 1. أغلق التطبيق/المتصفح 2. افتحه بعد 30 دقيقة | G8: يفتح مباشرة دون طلب دخول | H8: متوسطة | I8: نعم | J8: Refresh_rotates_the_cookie_and_issues_a_working_token | K8: نجح | L8: فُتح التطبيق من جديد بدون طلب دخول | M8: Claude (اختبار آلي للشاشات) | N8: 46321
A9: AUTH-08 | B9: تسجيل الدخول والحساب | C9: تسجيل الخروج | D9: أي مستخدم | E9: مسجّل دخول | F9: 1. الحساب الشخصي ← تسجيل الخروج 2. اضغط زر الرجوع في المتصفح | G9: تظهر صفحة الدخول ولا يمكن الرجوع للبيانات | H9: عالية | I9: نعم | J9: Logout_revokes_the_refresh_token | K9: نجح | L9: مطابق للمتوقع | M9: Claude (اختبار آلي للشاشات) | N9: 46321
A10: AUTH-09 | B10: تسجيل الدخول والحساب | C10: مستخدم معطّل لا يستطيع الدخول | D10: أي مستخدم | E10: عطّل مستخدمًا من شاشة المستخدمين | F10: 1. حاول الدخول بحساب المستخدم المعطّل | G10: يُرفض الدخول | H10: عالية | I10: نعم | J10: A_deactivated_user_cannot_sign_in | K10: نجح | L10: مطابق للمتوقع | M10: Claude (اختبار آلي للشاشات) | N10: 46321
A11: AUTH-10 | B11: تسجيل الدخول والحساب | C11: إظهار/إخفاء كلمة المرور | D11: أي مستخدم | E11: — | F11: 1. اكتب كلمة المرور 2. اضغط أيقونة العين | G11: تظهر الكلمة ثم تختفي عند الضغط مرة أخرى | H11: منخفضة | I11: لا | J11: — | K11: نجح | L11: مطابق للمتوقع | M11: Claude (اختبار آلي للشاشات) | N11: 46321
A12: USR-01 | B12: المستخدمون والأدوار والصلاحيات | C12: إضافة مستخدم بدور «موظف مبيعات» | D12: مدير النظام | E12: — | F12: 1. المستخدمون ← إضافة 2. الاسم، اسم المستخدم، كلمة مرور مؤقتة، الدور 3. احفظ | G12: يظهر المستخدم في القائمة ويستطيع الدخول | H12: عالية | I12: نعم | J12: After_changing_the_password_only_the_new_one_works | K12: نجح | L12: مطابق للمتوقع | M12: Claude (اختبار آلي للشاشات) | N12: 46321
A13: USR-02 | B13: المستخدمون والأدوار والصلاحيات | C13: اسم مستخدم مكرر | D13: مدير النظام | E13: يوجد مستخدم باسم ahmad | F13: 1. أضف مستخدمًا جديدًا بنفس اسم المستخدم | G13: خطأ تحت حقل اسم المستخدم «مستخدم مسبقًا» ولا يُنشأ | H13: متوسطة | I13: نعم | J13: Duplicate_username_is_reported_on_the_username_field | K13: نجح | L13: مطابق للمتوقع | M13: Claude (اختبار آلي للشاشات) | N13: 46321
... A150: CON-04 | B150: التزامن وسلامة البيانات | C150: رصيد الحساب = مجموع حركاته دائمًا | D150: محاسب | E150: حركات كثيرة | F150: 1. قارن رصيد الحساب بآخر رصيد في كشفه | G150: متطابقان | H150: عالية | I150: نعم | J150: Opening_balance_is_posted_as_a_movement_and_the_balance_always_equals_the_movements | K150: نجح | L150: 6 حسابات: الرصيد = آخر رصيد في الكشف | M150: Claude (اختبار آلي للشاشات) | N150: 46321

Sheet الملخص
A1: ملخص نتائج الاختبار — نظام معرض قويدر
A2: يتحدث تلقائيًا من عمود «النتيجة» في ورقة «حالات الاختبار».
A4: القسم | B4: عدد الحالات | C4: نجح | D4: فشل | E4: محجوب | F4: لم يُختبر | G4: مغطى آليًا | H4: نسبة الإنجاز | I4: نسبة النجاح
A5: تسجيل الدخول والحساب | B5: =COUNTIF('حالات الاختبار'!$B$2:$B$150,A5) -> 10 | C5: =COUNTIFS('حالات الاختبار'!$B$2:$B$150,$A5,'حالات الاختبار'!$K$2:$K$150,"نجح") -> 10 | D5: =COUNTIFS('حالات الاختبار'!$B$2:$B$150,$A5,'حالات الاختبار'!$K$2:$K$150,"فشل") -> 0 | E5: =COUNTIFS('حالات الاختبار'!$B$2:$B$150,$A5,'حالات الاختبار'!$K$2:$K$150,"محجوب") -> 0 | F5: =B5-C5-D5-E5 -> 0 | G5: =COUNTIFS('حالات الاختبار'!$B$2:$B$150,$A5,'حالات الاختبار'!$I$2:$I$150,"نعم") -> 9 | H5: =IF(B5=0,0,(C5+D5+E5)/B5) -> 1 | I5: =IF(C5+D5=0,0,C5/(C5+D5)) -> 1
A6: المستخدمون والأدوار والصلاحيات | B6: =COUNTIF('حالات الاختبار'!$B$2:$B$150,A6) -> 10 | C6: =COUNTIFS('حالات الاختبار'!$B$2:$B$150,$A6,'حالات الاختبار'!$K$2:$K$150,"نجح") -> 10 | D6: =COUNTIFS('حالات الاختبار'!$B$2:$B$150,$A6,'حالات الاختبار'!$K$2:$K$150,"فشل") -> 0 | E6: =COUNTIFS('حالات الاختبار'!$B$2:$B$150,$A6,'حالات الاختبار'!$K$2:$K$150,"محجوب") -> 0 | F6: =B6-C6-D6-E6 -> 0 | G6: =COUNTIFS('حالات الاختبار'!$B$2:$B$150,$A6,'حالات الاختبار'!$I$2:$I$150,"نعم") -> 8 | H6: =IF(B6=0,0,(C6+D6+E6)/B6) -> 1 | I6: =IF(C6+D6=0,0,C6/(C6+D6)) -> 1
A7: الإعدادات وسجل العمليات والتصفير | B7: =COUNTIF('حالات الاختبار'!$B$2:$B$150,A7) -> 9 | C7: =COUNTIFS('حالات الاختبار'!$B$2:$B$150,$A7,'حالات الاختبار'!$K$2:$K$150,"نجح") -> 9 | D7: =COUNTIFS('حالات الاختبار'!$B$2:$B$150,$A7,'حالات الاختبار'!$K$2:$K$150,"فشل") -> 0 | E7: =COUNTIFS('حالات الاختبار'!$B$2:$B$150,$A7,'حالات الاختبار'!$K$2:$K$150,"محجوب") -> 0 | F7: =B7-C7-D7-E7 -> 0 | G7: =COUNTIFS('حالات الاختبار'!$B$2:$B$150,$A7,'حالات الاختبار'!$I$2:$I$150,"نعم") -> 9 | H7: =IF(B7=0,0,(C7+D7+E7)/B7) -> 1 | I7: =IF(C7+D7=0,0,C7/(C7+D7)) -> 1
A8: الأصناف | B8: =COUNTIF('حالات الاختبار'!$B$2:$B$150,A8) -> 4 | C8: =COUNTIFS('حالات الاختبار'!$B$2:$B$150,$A8,'حالات الاختبار'!$K$2:$K$150,"نجح") -> 4 | D8: =COUNTIFS('حالات الاختبار'!$B$2:$B$150,$A8,'حالات الاختبار'!$K$2:$K$150,"فشل") -> 0 | E8: =COUNTIFS('حالات الاختبار'!$B$2:$B$150,$A8,'حالات الاختبار'!$K$2:$K$150,"محجوب") -> 0 | F8: =B8-C8-D8-E8 -> 0 | G8: =COUNTIFS('حالات الاختبار'!$B$2:$B$150,$A8,'حالات الاختبار'!$I$2:$I$150,"نعم") -> 0 | H8: =IF(B8=0,0,(C8+D8+E8)/B8) -> 1 | I8: =IF(C8+D8=0,0,C8/(C8+D8)) -> 1
A9: المنتجات والباركود | B9: =COUNTIF('حالات الاختبار'!$B$2:$B$150,A9) -> 14 | C9: =COUNTIFS('حالات الاختبار'!$B$2:$B$150,$A9,'حالات الاختبار'!$K$2:$K$150,"نجح") -> 13 | D9: =COUNTIFS('حالات الاختبار'!$B$2:$B$150,$A9,'حالات الاختبار'!$K$2:$K$150,"فشل") -> 0 | E9: =COUNTIFS('حالات الاختبار'!$B$2:$B$150,$A9,'حالات الاختبار'!$K$2:$K$150,"محجوب") -> 1 | F9: =B9-C9-D9-E9 -> 0 | G9: =COUNTIFS('حالات الاختبار'!$B$2:$B$150,$A9,'حالات الاختبار'!$I$2:$I$150,"نعم") -> 10 | H9: =IF(B9=0,0,(C9+D9+E9)/B9) -> 1 | I9: =IF(C9+D9=0,0,C9/(C9+D9)) -> 1
A10: المخزون والجرد | B10: =COUNTIF('حالات الاختبار'!$B$2:$B$150,A10) -> 6 | C10: =COUNTIFS('حالات الاختبار'!$B$2:$B$150,$A10,'حالات الاختبار'!$K$2:$K$150,"نجح") -> 6 | D10: =COUNTIFS('حالات الاختبار'!$B$2:$B$150,$A10,'حالات الاختبار'!$K$2:$K$150,"فشل") -> 0 | E10: =COUNTIFS('حالات الاختبار'!$B$2:$B$150,$A10,'حالات الاختبار'!$K$2:$K$150,"محجوب") -> 0 | F10: =B10-C10-D10-E10 -> 0 | G10: =COUNTIFS('حالات الاختبار'!$B$2:$B$150,$A10,'حالات الاختبار'!$I$2:$I$150,"نعم") -> 4 | H10: =IF(B10=0,0,(C10+D10+E10)/B10) -> 1 | I10: =IF(C10+D10=0,0,C10/(C10+D10)) -> 1
A11: الموردون والمشتريات | B11: =COUNTIF('حالات الاختبار'!$B$2:$B$150,A11) -> 7 | C11: =COUNTIFS('حالات الاختبار'!$B$2:$B$150,$A11,'حالات الاختبار'!$K$2:$K$150,"نجح") -> 7 | D11: =COUNTIFS('حالات الاختبار'!$B$2:$B$150,$A11,'حالات الاختبار'!$K$2:$K$150,"فشل") -> 0 | E11: =COUNTIFS('حالات الاختبار'!$B$2:$B$150,$A11,'حالات الاختبار'!$K$2:$K$150,"محجوب") -> 0 | F11: =B11-C11-D11-E11 -> 0 | G11: =COUNTIFS('حالات الاختبار'!$B$2:$B$150,$A11,'حالات الاختبار'!$I$2:$I$150,"نعم") -> 6 | H11: =IF(B11=0,0,(C11+D11+E11)/B11) -> 1 | I11: =IF(C11+D11=0,0,C11/(C11+D11)) -> 1
A12: نقطة البيع | B12: =COUNTIF('حالات الاختبار'!$B$2:$B$150,A12) -> 16 | C12: =COUNTIFS('حالات الاختبار'!$B$2:$B$150,$A12,'حالات الاختبار'!$K$2:$K$150,"نجح") -> 16 | D12: =COUNTIFS('حالات الاختبار'!$B$2:$B$150,$A12,'حالات الاختبار'!$K$2:$K$150,"فشل") -> 0 | E12: =COUNTIFS('حالات الاختبار'!$B$2:$B$150,$A12,'حالات الاختبار'!$K$2:$K$150,"محجوب") -> 0 | F12: =B12-C12-D12-E12 -> 0 | G12: =COUNTIFS('حالات الاختبار'!$B$2:$B$150,$A12,'حالات الاختبار'!$I$2:$I$150,"نعم") -> 11 | H12: =IF(B12=0,0,(C12+D12+E12)/B12) -> 1 | I12: =IF(C12+D12=0,0,C12/(C12+D12)) -> 1
A13: فواتير المبيعات والمرتجعات | B13: =COUNTIF('حالات الاختبار'!$B$2:$B$150,A13) -> 11 | C13: =COUNTIFS('حالات الاختبار'!$B$2:$B$150,$A13,'حالات الاختبار'!$K$2:$K$150,"نجح") -> 11 | D13: =COUNTIFS('حالات الاختبار'!$B$2:$B$150,$A13,'حالات الاختبار'!$K$2:$K$150,"فشل") -> 0 | E13: =COUNTIFS('حالات الاختبار'!$B$2:$B$150,$A13,'حالات الاختبار'!$K$2:$K$150,"محجوب") -> 0 | F13: =B13-C13-D13-E13 -> 0 | G13: =COUNTIFS('حالات الاختبار'!$B$2:$B$150,$A13,'حالات الاختبار'!$I$2:$I$150,"نعم") -> 8 | H13: =IF(B13=0,0,(C13+D13+E13)/B13) -> 1 | I13: =IF(C13+D13=0,0,C13/(C13+D13)) -> 1
A14: العملاء والديون | B14: =COUNTIF('حالات الاختبار'!$B$2:$B$150,A14) -> 5 | C14: =COUNTIFS('حالات الاختبار'!$B$2:$B$150,$A14,'حالات الاختبار'!$K$2:$K$150,"نجح") -> 5 | D14: =COUNTIFS('حالات الاختبار'!$B$2:$B$150,$A14,'حالات الاختبار'!$K$2:$K$150,"فشل") -> 0 | E14: =COUNTIFS('حالات الاختبار'!$B$2:$B$150,$A14,'حالات الاختبار'!$K$2:$K$150,"محجوب") -> 0 | F14: =B14-C14-D14-E14 -> 0 | G14: =COUNTIFS('حالات الاختبار'!$B$2:$B$150,$A14,'حالات الاختبار'!$I$2:$I$150,"نعم") -> 1 | H14: =IF(B14=0,0,(C14+D14+E14)/B14) -> 1 | I14: =IF(C14+D14=0,0,C14/(C14+D14)) -> 1
A15: الحوالات | B15: =COUNTIF('حالات الاختبار'!$B$2:$B$150,A15) -> 6 | C15: =COUNTIFS('حالات الاختبار'!$B$2:$B$150,$A15,'حالات الاختبار'!$K$2:$K$150,"نجح") -> 6 | D15: =COUNTIFS('حالات الاختبار'!$B$2:$B$150,$A15,'حالات الاختبار'!$K$2:$K$150,"فشل") -> 0 | E15: =COUNTIFS('حالات الاختبار'!$B$2:$B$150,$A15,'حالات الاختبار'!$K$2:$K$150,"محجوب") -> 0 | F15: =B15-C15-D15-E15 -> 0 | G15: =COUNTIFS('حالات الاختبار'!$B$2:$B$150,$A15,'حالات الاختبار'!$I$2:$I$150,"نعم") -> 4 | H15: =IF(B15=0,0,(C15+D15+E15)/B15) -> 1 | I15: =IF(C15+D15=0,0,C15/(C15+D15)) -> 1
A16: الحسابات المالية والتحويلات | B16: =COUNTIF('حالات الاختبار'!$B$2:$B$150,A16) -> 5 | C16: =COUNTIFS('حالات الاختبار'!$B$2:$B$150,$A16,'حالات الاختبار'!$K$2:$K$150,"نجح") -> 5 | D16: =COUNTIFS('حالات الاختبار'!$B$2:$B$150,$A16,'حالات الاختبار'!$K$2:$K$150,"فشل") -> 0 | E16: =COUNTIFS('حالات الاختبار'!$B$2:$B$150,$A16,'حالات الاختبار'!$K$2:$K$150,"محجوب") -> 0 | F16: =B16-C16-D16-E16 -> 0 | G16: =COUNTIFS('حالات الاختبار'!$B$2:$B$150,$A16,'حالات الاختبار'!$I$2:$I$150,"نعم") -> 5 | H16: =IF(B16=0,0,(C16+D16+E16)/B16) -> 1 | I16: =IF(C16+D16=0,0,C16/(C16+D16)) -> 1
... A24: التزامن وسلامة البيانات | B24: =COUNTIF('حالات الاختبار'!$B$2:$B$150,A24) -> 4 | C24: =COUNTIFS('حالات الاختبار'!$B$2:$B$150,$A24,'حالات الاختبار'!$K$2:$K$150,"نجح") -> 4 | D24: =COUNTIFS('حالات الاختبار'!$B$2:$B$150,$A24,'حالات الاختبار'!$K$2:$K$150,"فشل") -> 0 | E24: =COUNTIFS('حالات الاختبار'!$B$2:$B$150,$A24,'حالات الاختبار'!$K$2:$K$150,"محجوب") -> 0 | F24: =B24-C24-D24-E24 -> 0 | G24: =COUNTIFS('حالات الاختبار'!$B$2:$B$150,$A24,'حالات الاختبار'!$I$2:$I$150,"نعم") -> 4 | H24: =IF(B24=0,0,(C24+D24+E24)/B24) -> 1 | I24: =IF(C24+D24=0,0,C24/(C24+D24)) -> 1
A25: الإجمالي | B25: =SUM(B5:B24) -> 149 | C25: =SUM(C5:C24) -> 144 | D25: =SUM(D5:D24) -> 1 | E25: =SUM(E5:E24) -> 4 | F25: =SUM(F5:F24) -> 0 | G25: =SUM(G5:G24) -> 101 | H25: =IF(B25=0,0,(C25+D25+E25)/B25) -> 1 | I25: =IF(C25+D25=0,0,C25/(C25+D25)) -> 0.99310345
A28: حسب الأولوية
A29: الأولوية | B29: عدد الحالات | C29: نجح | D29: فشل | E29: لم يُختبر
A30: عالية | B30: =COUNTIF('حالات الاختبار'!$H$2:$H$150,A30) -> 81 | C30: =COUNTIFS('حالات الاختبار'!$H$2:$H$150,$A30,'حالات الاختبار'!$K$2:$K$150,"نجح") -> 80 | D30: =COUNTIFS('حالات الاختبار'!$H$2:$H$150,$A30,'حالات الاختبار'!$K$2:$K$150,"فشل") -> 0 | E30: =COUNTIFS('حالات الاختبار'!$H$2:$H$150,$A30,'حالات الاختبار'!$K$2:$K$150,"لم يُختبر") -> 0
A31: متوسطة | B31: =COUNTIF('حالات الاختبار'!$H$2:$H$150,A31) -> 56 | C31: =COUNTIFS('حالات الاختبار'!$H$2:$H$150,$A31,'حالات الاختبار'!$K$2:$K$150,"نجح") -> 53 | D31: =COUNTIFS('حالات الاختبار'!$H$2:$H$150,$A31,'حالات الاختبار'!$K$2:$K$150,"فشل") -> 1 | E31: =COUNTIFS('حالات الاختبار'!$H$2:$H$150,$A31,'حالات الاختبار'!$K$2:$K$150,"لم يُختبر") -> 0
A32: منخفضة | B32: =COUNTIF('حالات الاختبار'!$H$2:$H$150,A32) -> 12 | C32: =COUNTIFS('حالات الاختبار'!$H$2:$H$150,$A32,'حالات الاختبار'!$K$2:$K$150,"نجح") -> 11 | D32: =COUNTIFS('حالات الاختبار'!$H$2:$H$150,$A32,'حالات الاختبار'!$K$2:$K$150,"فشل") -> 0 | E32: =COUNTIFS('حالات الاختبار'!$H$2:$H$150,$A32,'حالات الاختبار'!$K$2:$K$150,"لم يُختبر") -> 0
A34: جاهز للتشغيل الفعلي عندما: كل حالات الأولوية «عالية» = نجح، ولا يوجد «فشل» مفتوح.
